mouse_patrol/__init__.py
mouse_patrol/main.py
mouse_patrol-0.3.0.dist-info/licenses/LICENSE
mouse_patrol-0.3.0.dist-info/METADATA
mouse_patrol-0.3.0.dist-info/WHEEL
mouse_patrol-0.3.0.dist-info/entry_points.txt
mouse_patrol-0.3.0.dist-info/top_level.txt
mouse_patrol-0.3.0.dist-info/RECORD
