Metadata-Version: 2.4
Name: mouse-patrol
Version: 0.3.0
Summary: Python utility to automatically & regularly move your mouse to prevent going idle
Author-email: Leon Bojanowski <leongaborbojanowski04@gmail.com>
Maintainer-email: Leon Bojanowski <leongaborbojanowski04@gmail.com>
License: MIT License
Project-URL: Homepage, https://github.com/f1nal04/mouse-patrol
Project-URL: Repository, https://github.com/f1nal04/mouse-patrol.git
Project-URL: Issues, https://github.com/f1nal04/mouse-patrol/issues
Keywords: mouse,automation,idle,screensaver,pyautogui
Classifier: Development Status :: 3 - Alpha
Classifier: Intended Audience :: End Users/Desktop
Classifier: License :: OSI Approved :: MIT License
Classifier: Operating System :: OS Independent
Classifier: Programming Language :: Python :: 3
Classifier: Programming Language :: Python :: 3.8
Classifier: Programming Language :: Python :: 3.9
Classifier: Programming Language :: Python :: 3.10
Classifier: Programming Language :: Python :: 3.11
Classifier: Programming Language :: Python :: 3.12
Classifier: Topic :: Desktop Environment
Classifier: Topic :: System :: Systems Administration
Classifier: Topic :: Utilities
Requires-Python: >=3.8
License-File: LICENSE
Requires-Dist: pyautogui
Requires-Dist: rich
Dynamic: license-file
